LICENSE
MANIFEST.in
README.rst
requirements.txt
setup.py
docs/examples/parrot.py
docs/examples/upload.py
volapi/__init__.py
volapi/arbritrator.py
volapi/auxo.py
volapi/chat.py
volapi/config.py
volapi/constants.py
volapi/file.py
volapi/handler.py
volapi/multipart.py
volapi/user.py
volapi/utils.py
volapi/volapi.py
volapi.egg-info/PKG-INFO
volapi.egg-info/SOURCES.txt
volapi.egg-info/dependency_links.txt
volapi.egg-info/requires.txt
volapi.egg-info/top_level.txt