Metadata-Version: 1.1
Name: volapi
Version: 5.16.0
Summary: API for Volafile.org
Home-page: https://github.com/volafiled/python-volapi
Author: RealDolos, szero
Author-email: dolos@cock.li, singleton@tfwno.gf
License: MIT
Platform: UNKNOWN
Classifier: Development Status :: 5 - Production/Stable
Classifier: Intended Audience :: Developers
Classifier: Natural Language :: English
Classifier: License :: OSI Approved :: MIT License
Classifier: Operating System :: OS Independent
Classifier: Programming Language :: Python
Classifier: Programming Language :: Python :: 3.6
Classifier: Programming Language :: Python :: 3.7
Classifier: Programming Language :: Python :: 3 :: Only
Classifier: Topic :: Software Development :: Libraries :: Python Modules
